tool_registry_module/__init__.py
tool_registry_module/_json_schema.py
tool_registry_module/registry_builders.py
tool_registry_module/tool_context_type.py
tool_registry_module/tool_registry.py
ai_tool_registry-0.7.6.dist-info/METADATA
ai_tool_registry-0.7.6.dist-info/WHEEL
ai_tool_registry-0.7.6.dist-info/licenses/LICENSE
ai_tool_registry-0.7.6.dist-info/RECORD
