Metadata-Version: 2.4
Name: ai-tool-registry
Version: 0.7.6
Summary: Advanced tool registration system for Anthropic Claude integration with automatic schema generation and validation
Project-URL: Homepage, https://github.com/kazmer97/ai-tool-registry
Project-URL: Repository, https://github.com/kazmer97/ai-tool-registry
Project-URL: Documentation, https://github.com/kazmer97/ai-tool-registry#readme
Project-URL: Bug Tracker, https://github.com/kazmer97/ai-tool-registry/issues
Author-email: "Kazmer, Nagy-Betegh" <kazmer.nb@gmail.com>
License: MIT
License-File: LICENSE
Keywords: anthropic,api,claude,schema,tools,validation
Classifier: Development Status :: 4 - Beta
Classifier: Intended Audience :: Developers
Classifier: License :: OSI Approved :: MIT License
Classifier: Programming Language :: Python :: 3
Classifier: Programming Language :: Python :: 3.12
Classifier: Programming Language :: Python :: 3.13
Classifier: Topic :: Internet :: WWW/HTTP :: Dynamic Content
Classifier: Topic :: Software Development :: Libraries :: Python Modules
Requires-Python: >=3.12
Requires-Dist: pydantic>=2.0.0
Provides-Extra: all
Requires-Dist: anthropic>=0.52.2; extra == 'all'
Requires-Dist: boto3>=1.34.0; extra == 'all'
Requires-Dist: google-generativeai>=0.3.0; extra == 'all'
Requires-Dist: mistralai>=0.4.0; extra == 'all'
Requires-Dist: openai>=1.0.0; extra == 'all'
Provides-Extra: anthropic
Requires-Dist: anthropic>=0.52.2; extra == 'anthropic'
Provides-Extra: bedrock
Requires-Dist: boto3>=1.34.0; extra == 'bedrock'
Provides-Extra: gemini
Requires-Dist: google-generativeai>=0.3.0; extra == 'gemini'
Provides-Extra: mistral
Requires-Dist: mistralai>=0.4.0; extra == 'mistral'
Provides-Extra: openai
Requires-Dist: openai>=1.0.0; extra == 'openai'
